aiolang2/__init__.py
aiolang2/exceptions.py
aiolang2/google.py
aiolang2/langs.py
aiolang2/translate.py
aiolang2-0.0.1.dist-info/LICENSE
aiolang2-0.0.1.dist-info/METADATA
aiolang2-0.0.1.dist-info/WHEEL
aiolang2-0.0.1.dist-info/top_level.txt
aiolang2-0.0.1.dist-info/RECORD
